pyrancell/__init__.py
pyrancell/apis/__init__.py
pyrancell/apis/api.py
pyrancell/client/__init__.py
pyrancell/client/client.py
pyrancell/headers/__init__.py
pyrancell/headers/header.py
pyrancell/methods/__init__.py
pyrancell/methods/method.py
pyrancell-1.0.1.dist-info/METADATA
pyrancell-1.0.1.dist-info/WHEEL
pyrancell-1.0.1.dist-info/top_level.txt
pyrancell-1.0.1.dist-info/RECORD
