Metadata-Version: 2.4
Name: pyrancell
Version: 1.0.1
Author: Danial Erfan Dost
License: MIT
Project-URL: Homepage, https://github.com/NOMASKERFAN
Keywords: example,package
Requires-Python: >=3.7
